confio/__init__.py
confio/__meta__.py
confio/core/__init__.py
confio/core/base.py
confio/core/parser.py
confio/misc/__init__.py
confio/misc/utils.py
confio/providers/__init__.py
confio/providers/consul.py
confio/providers/db.py
confio/providers/db_dameng.py
confio/providers/db_mysql.py
confio/providers/fs.py
confio-0.5.0.dist-info/LICENSE
confio-0.5.0.dist-info/METADATA
confio-0.5.0.dist-info/WHEEL
confio-0.5.0.dist-info/top_level.txt
confio-0.5.0.dist-info/RECORD
