Metadata-Version: 2.1
Name: confio
Version: 0.5.0
Summary: Configurations IO for various of data sources with unified interfaces.
Home-page: https://gitee.com/wangankeji/confio
Author: hyjiacan
Author-email: hyjiacan@163.com
Maintainer: hyjiacan
Maintainer-email: hyjiacan@163.com
License: UNKNOWN
Project-URL: Documentation, https://gitee.com/wangankeji/confio/wikis
Project-URL: Repository, https://gitee.com/wangankeji/confio
Project-URL: Issue tracker, https://gitee.com/wangankeji/confio/issues
Platform: UNKNOWN
Classifier: Development Status :: 4 - Beta
Classifier: Environment :: Web Environment
Classifier: Intended Audience :: Developers
Classifier: License :: OSI Approved :: MIT License
Classifier: Operating System :: OS Independent
Classifier: Programming Language :: Python :: 3
Requires-Python: >=3.5
